sopel_inclusivity/__init__.py
sopel_inclusivity/plugin.py
sopel_inclusivity-0.3.0.dist-info/COPYING
sopel_inclusivity-0.3.0.dist-info/METADATA
sopel_inclusivity-0.3.0.dist-info/WHEEL
sopel_inclusivity-0.3.0.dist-info/entry_points.txt
sopel_inclusivity-0.3.0.dist-info/top_level.txt
sopel_inclusivity-0.3.0.dist-info/RECORD
