Metadata-Version: 2.1
Name: sopel-inclusivity
Version: 0.3.0
Summary: Have your Sopel bot suggest more inclusive language
Author: Elsie Powell
Maintainer-email: dgw <dgw@technobabbl.es>
License: EFL-2.0
Project-URL: Homepage, https://github.com/sopel-irc/sopel-inclusivity
Project-URL: Bug Tracker, https://github.com/sopel-irc/sopel-inclusivity/issues
Keywords: sopel,plugin,bot,irc
Platform: Linux x86, x86-64
Classifier: Development Status :: 4 - Beta
Classifier: Intended Audience :: Developers
Classifier: Intended Audience :: System Administrators
Classifier: License :: Eiffel Forum License (EFL)
Classifier: License :: OSI Approved :: Eiffel Forum License
Classifier: Programming Language :: Python :: 3 :: Only
Classifier: Programming Language :: Python :: 3.8
Classifier: Programming Language :: Python :: 3.9
Classifier: Programming Language :: Python :: 3.10
Classifier: Programming Language :: Python :: 3.11
Classifier: Programming Language :: Python :: 3.12
Classifier: Topic :: Communications :: Chat :: Internet Relay Chat
Requires-Python: <4,>=3.8
License-File: COPYING
Requires-Dist: sopel >=7.1
